space_setup/__init__.py
space_setup/host.bat
space_setup/host.py
space_setup/main-setup.py
space_setup/main.py
space_setup/setup-django-sslserver.py
space_setup/setupSslserver.py
space_setup/setup_heroku.py
space_setup/shell.py
temp/__init__.py
temp/static/.nomedia.txt
temp/static/css/all.css
temp/static/css/animate.css
temp/static/css/bootstrap-icons.css
temp/static/css/bootstrap.css
temp/static/css/navbar-static-top.css
temp/static/css/navbar-top.css
temp/static/css/fonts/bootstrap-icons.woff
temp/static/css/fonts/bootstrap-icons.woff2
temp/static/images/LoginFail.jpg
temp/static/images/Mabout.jpg
temp/static/images/bg.jpg
temp/static/images/contact_banner.jpg
temp/static/images/default.png
temp/static/images/favicon.ico
temp/static/images/home_banner.jpg
temp/static/images/image1.jpg
temp/static/images/image2.jpg
temp/static/images/image3.jpg
temp/static/images/image4.jpg
temp/static/images/image5.jpg
temp/static/images/login.jpg
temp/static/images/navbkgd.jpg
temp/static/images/register.jpg
temp/static/images/terms_banner.jpg
temp/static/javascript/bootstrap-notify.js
temp/static/javascript/bootstrap.js
temp/static/javascript/jquery.js
temp/templates/__init__.py
temp/templates/base.html
temp/templates/baseFull.html
temp/templates/bootstrap5.py
temp/templates/home.html
temp/templates/home[old].html
temp/templates/navbar.html
temp/templates/bootstrap5/accordion-group.html
temp/templates/bootstrap5/accordion.html
temp/templates/bootstrap5/betterform.html
temp/templates/bootstrap5/display_form.html
temp/templates/bootstrap5/errors.html
temp/templates/bootstrap5/errors_formset.html
temp/templates/bootstrap5/field.html
temp/templates/bootstrap5/inputs.html
temp/templates/bootstrap5/table_inline_formset.html
temp/templates/bootstrap5/uni_form.html
temp/templates/bootstrap5/uni_formset.html
temp/templates/bootstrap5/whole_uni_form.html
temp/templates/bootstrap5/whole_uni_formset.html
temp/templates/bootstrap5/layout/alert.html
django_space-0.0.0.17.3.dist-info/LICENSE
django_space-0.0.0.17.3.dist-info/METADATA
django_space-0.0.0.17.3.dist-info/WHEEL
django_space-0.0.0.17.3.dist-info/entry_points.txt
django_space-0.0.0.17.3.dist-info/top_level.txt
django_space-0.0.0.17.3.dist-info/RECORD
