Metadata-Version: 2.1
Name: django-space
Version: 0.0.0.17.3
Summary: This package is setup a django project in quick way.
Author: rshnthms
Author-email: 
License: BSD-3-Clause
Classifier: Development Status :: 1 - Planning
Classifier: Intended Audience :: Developers
Classifier: Operating System :: OS Independent
Classifier: Programming Language :: Python
Classifier: Programming Language :: Python :: 3
Classifier: Programming Language :: Python :: 3 :: Only
Classifier: Programming Language :: Python :: 3.8
Classifier: Programming Language :: Python :: 3.9
Classifier: Programming Language :: Python :: 3.10
Classifier: Programming Language :: Python :: 3.11
Classifier: Programming Language :: Python :: 3.12
Classifier: Topic :: Internet :: WWW/HTTP
Classifier: Topic :: Internet :: WWW/HTTP :: Dynamic Content
Classifier: Topic :: Internet :: WWW/HTTP :: WSGI
Classifier: Topic :: Software Development :: Libraries :: Application Frameworks
Classifier: Topic :: Software Development :: Libraries :: Python Modules
Requires-Python: <=3.12.2
License-File: LICENSE
Requires-Dist: django ==5.0.2
Requires-Dist: django-sslserver-v2 ==1.0
Requires-Dist: django-sslserver ==0.22
Requires-Dist: django-registration-redux ==2.13
Requires-Dist: django-crispy-forms ==2.1
Requires-Dist: djangorestframework ==3.14.0
Requires-Dist: django-rest-knox ==4.2.0
Requires-Dist: whitenoise ==6.6.0
Requires-Dist: requests ==2.31.0
